{
  "model": "Set2Set",
  "mean_test_acc": 0.7224322758221063,
  "std_test_acc": 0.05587717487804046,
  "folds": [
    {
      "fold": 1,
      "val_acc": 0.7264150943396226,
      "test_acc": 0.8135593220338984,
      "test_loss": 0.4816188802153377,
      "best_override": {
        "set2set_steps": 3
      },
      "best_cfg": {
        "hidden_dim": 64,
        "num_conv_layers": 3,
        "dropout": 0.0,
        "lr": null,
        "pool_ratio": 0.5,
        "num_pools": 3,
        "sort_k": 30,
        "sort_conv1d_out": 32,
        "sort_conv1d_kernel": 5,
        "set2set_steps": 3,
        "set2set_layers": 1,
        "gmt_k": 30,
        "gmt_heads": 4,
        "gmt_encoder_blocks": 1,
        "gmt_dropout": 0.0,
        "gmt_layer_norm": false,
        "dense_pool_layers": 2,
        "diffpool_ratio_1": 0.25,
        "diffpool_ratio_2": 0.25,
        "mincut_ratio_1": 0.5,
        "mincut_ratio_2": 0.5,
        "diffpool_link_loss_weight": 1.0,
        "diffpool_entropy_loss_weight": 1.0,
        "mincut_loss_weight": 1.0,
        "mincut_ortho_loss_weight": 1.0,
        "dense_max_nodes": null,
        "dense_policy": "error",
        "degree_as_feature": true,
        "degree_onehot_cap": 100
      },
      "train_info": {
        "best_epoch": 56,
        "best_val_acc": 0.7264150943396226,
        "final_val_acc": 0.7264150943396226,
        "final_val_loss": 0.6657479776526397
      }
    },
    {
      "fold": 2,
      "val_acc": 0.7547169811320755,
      "test_acc": 0.7203389830508474,
      "test_loss": 0.5929251929460946,
      "best_override": {
        "set2set_steps": 3
      },
      "best_cfg": {
        "hidden_dim": 64,
        "num_conv_layers": 3,
        "dropout": 0.0,
        "lr": null,
        "pool_ratio": 0.5,
        "num_pools": 3,
        "sort_k": 30,
        "sort_conv1d_out": 32,
        "sort_conv1d_kernel": 5,
        "set2set_steps": 3,
        "set2set_layers": 1,
        "gmt_k": 30,
        "gmt_heads": 4,
        "gmt_encoder_blocks": 1,
        "gmt_dropout": 0.0,
        "gmt_layer_norm": false,
        "dense_pool_layers": 2,
        "diffpool_ratio_1": 0.25,
        "diffpool_ratio_2": 0.25,
        "mincut_ratio_1": 0.5,
        "mincut_ratio_2": 0.5,
        "diffpool_link_loss_weight": 1.0,
        "diffpool_entropy_loss_weight": 1.0,
        "mincut_loss_weight": 1.0,
        "mincut_ortho_loss_weight": 1.0,
        "dense_max_nodes": null,
        "dense_policy": "error",
        "degree_as_feature": true,
        "degree_onehot_cap": 100
      },
      "train_info": {
        "best_epoch": 66,
        "best_val_acc": 0.7547169811320755,
        "final_val_acc": 0.7547169811320755,
        "final_val_loss": 0.5898393291347431
      }
    },
    {
      "fold": 3,
      "val_acc": 0.7924528301886793,
      "test_acc": 0.7372881355932204,
      "test_loss": 0.5439174185364933,
      "best_override": {
        "set2set_steps": 6
      },
      "best_cfg": {
        "hidden_dim": 64,
        "num_conv_layers": 3,
        "dropout": 0.0,
        "lr": null,
        "pool_ratio": 0.5,
        "num_pools": 3,
        "sort_k": 30,
        "sort_conv1d_out": 32,
        "sort_conv1d_kernel": 5,
        "set2set_steps": 6,
        "set2set_layers": 1,
        "gmt_k": 30,
        "gmt_heads": 4,
        "gmt_encoder_blocks": 1,
        "gmt_dropout": 0.0,
        "gmt_layer_norm": false,
        "dense_pool_layers": 2,
        "diffpool_ratio_1": 0.25,
        "diffpool_ratio_2": 0.25,
        "mincut_ratio_1": 0.5,
        "mincut_ratio_2": 0.5,
        "diffpool_link_loss_weight": 1.0,
        "diffpool_entropy_loss_weight": 1.0,
        "mincut_loss_weight": 1.0,
        "mincut_ortho_loss_weight": 1.0,
        "dense_max_nodes": null,
        "dense_policy": "error",
        "degree_as_feature": true,
        "degree_onehot_cap": 100
      },
      "train_info": {
        "best_epoch": 57,
        "best_val_acc": 0.7924528301886793,
        "final_val_acc": 0.7924528301886793,
        "final_val_loss": 0.5347172910312437
      }
    },
    {
      "fold": 4,
      "val_acc": 0.7641509433962265,
      "test_acc": 0.6610169491525424,
      "test_loss": 0.7184127912683002,
      "best_override": {
        "set2set_steps": 3
      },
      "best_cfg": {
        "hidden_dim": 64,
        "num_conv_layers": 3,
        "dropout": 0.0,
        "lr": null,
        "pool_ratio": 0.5,
        "num_pools": 3,
        "sort_k": 30,
        "sort_conv1d_out": 32,
        "sort_conv1d_kernel": 5,
        "set2set_steps": 3,
        "set2set_layers": 1,
        "gmt_k": 30,
        "gmt_heads": 4,
        "gmt_encoder_blocks": 1,
        "gmt_dropout": 0.0,
        "gmt_layer_norm": false,
        "dense_pool_layers": 2,
        "diffpool_ratio_1": 0.25,
        "diffpool_ratio_2": 0.25,
        "mincut_ratio_1": 0.5,
        "mincut_ratio_2": 0.5,
        "diffpool_link_loss_weight": 1.0,
        "diffpool_entropy_loss_weight": 1.0,
        "mincut_loss_weight": 1.0,
        "mincut_ortho_loss_weight": 1.0,
        "dense_max_nodes": null,
        "dense_policy": "error",
        "degree_as_feature": true,
        "degree_onehot_cap": 100
      },
      "train_info": {
        "best_epoch": 53,
        "best_val_acc": 0.7641509433962265,
        "final_val_acc": 0.7641509433962265,
        "final_val_loss": 0.5621381998062134
      }
    },
    {
      "fold": 5,
      "val_acc": 0.8301886792452831,
      "test_acc": 0.7203389830508474,
      "test_loss": 0.5853266291699167,
      "best_override": {
        "set2set_steps": 3
      },
      "best_cfg": {
        "hidden_dim": 64,
        "num_conv_layers": 3,
        "dropout": 0.0,
        "lr": null,
        "pool_ratio": 0.5,
        "num_pools": 3,
        "sort_k": 30,
        "sort_conv1d_out": 32,
        "sort_conv1d_kernel": 5,
        "set2set_steps": 3,
        "set2set_layers": 1,
        "gmt_k": 30,
        "gmt_heads": 4,
        "gmt_encoder_blocks": 1,
        "gmt_dropout": 0.0,
        "gmt_layer_norm": false,
        "dense_pool_layers": 2,
        "diffpool_ratio_1": 0.25,
        "diffpool_ratio_2": 0.25,
        "mincut_ratio_1": 0.5,
        "mincut_ratio_2": 0.5,
        "diffpool_link_loss_weight": 1.0,
        "diffpool_entropy_loss_weight": 1.0,
        "mincut_loss_weight": 1.0,
        "mincut_ortho_loss_weight": 1.0,
        "dense_max_nodes": null,
        "dense_policy": "error",
        "degree_as_feature": true,
        "degree_onehot_cap": 100
      },
      "train_info": {
        "best_epoch": 14,
        "best_val_acc": 0.8301886792452831,
        "final_val_acc": 0.8301886792452831,
        "final_val_loss": 0.5334616966967313
      }
    },
    {
      "fold": 6,
      "val_acc": 0.7547169811320755,
      "test_acc": 0.7542372881355932,
      "test_loss": 0.6129936202097748,
      "best_override": {
        "set2set_steps": 3
      },
      "best_cfg": {
        "hidden_dim": 64,
        "num_conv_layers": 3,
        "dropout": 0.0,
        "lr": null,
        "pool_ratio": 0.5,
        "num_pools": 3,
        "sort_k": 30,
        "sort_conv1d_out": 32,
        "sort_conv1d_kernel": 5,
        "set2set_steps": 3,
        "set2set_layers": 1,
        "gmt_k": 30,
        "gmt_heads": 4,
        "gmt_encoder_blocks": 1,
        "gmt_dropout": 0.0,
        "gmt_layer_norm": false,
        "dense_pool_layers": 2,
        "diffpool_ratio_1": 0.25,
        "diffpool_ratio_2": 0.25,
        "mincut_ratio_1": 0.5,
        "mincut_ratio_2": 0.5,
        "diffpool_link_loss_weight": 1.0,
        "diffpool_entropy_loss_weight": 1.0,
        "mincut_loss_weight": 1.0,
        "mincut_ortho_loss_weight": 1.0,
        "dense_max_nodes": null,
        "dense_policy": "error",
        "degree_as_feature": true,
        "degree_onehot_cap": 100
      },
      "train_info": {
        "best_epoch": 73,
        "best_val_acc": 0.7547169811320755,
        "final_val_acc": 0.7547169811320755,
        "final_val_loss": 0.6401072088277565
      }
    },
    {
      "fold": 7,
      "val_acc": 0.7924528301886793,
      "test_acc": 0.7288135593220338,
      "test_loss": 0.5922901256609772,
      "best_override": {
        "set2set_steps": 6
      },
      "best_cfg": {
        "hidden_dim": 64,
        "num_conv_layers": 3,
        "dropout": 0.0,
        "lr": null,
        "pool_ratio": 0.5,
        "num_pools": 3,
        "sort_k": 30,
        "sort_conv1d_out": 32,
        "sort_conv1d_kernel": 5,
        "set2set_steps": 6,
        "set2set_layers": 1,
        "gmt_k": 30,
        "gmt_heads": 4,
        "gmt_encoder_blocks": 1,
        "gmt_dropout": 0.0,
        "gmt_layer_norm": false,
        "dense_pool_layers": 2,
        "diffpool_ratio_1": 0.25,
        "diffpool_ratio_2": 0.25,
        "mincut_ratio_1": 0.5,
        "mincut_ratio_2": 0.5,
        "diffpool_link_loss_weight": 1.0,
        "diffpool_entropy_loss_weight": 1.0,
        "mincut_loss_weight": 1.0,
        "mincut_ortho_loss_weight": 1.0,
        "dense_max_nodes": null,
        "dense_policy": "error",
        "degree_as_feature": true,
        "degree_onehot_cap": 100
      },
      "train_info": {
        "best_epoch": 52,
        "best_val_acc": 0.7924528301886793,
        "final_val_acc": 0.7924528301886793,
        "final_val_loss": 0.4971036708579873
      }
    },
    {
      "fold": 8,
      "val_acc": 0.839622641509434,
      "test_acc": 0.6186440677966102,
      "test_loss": 1.316844119863995,
      "best_override": {
        "set2set_steps": 6
      },
      "best_cfg": {
        "hidden_dim": 64,
        "num_conv_layers": 3,
        "dropout": 0.0,
        "lr": null,
        "pool_ratio": 0.5,
        "num_pools": 3,
        "sort_k": 30,
        "sort_conv1d_out": 32,
        "sort_conv1d_kernel": 5,
        "set2set_steps": 6,
        "set2set_layers": 1,
        "gmt_k": 30,
        "gmt_heads": 4,
        "gmt_encoder_blocks": 1,
        "gmt_dropout": 0.0,
        "gmt_layer_norm": false,
        "dense_pool_layers": 2,
        "diffpool_ratio_1": 0.25,
        "diffpool_ratio_2": 0.25,
        "mincut_ratio_1": 0.5,
        "mincut_ratio_2": 0.5,
        "diffpool_link_loss_weight": 1.0,
        "diffpool_entropy_loss_weight": 1.0,
        "mincut_loss_weight": 1.0,
        "mincut_ortho_loss_weight": 1.0,
        "dense_max_nodes": null,
        "dense_policy": "error",
        "degree_as_feature": true,
        "degree_onehot_cap": 100
      },
      "train_info": {
        "best_epoch": 221,
        "best_val_acc": 0.839622641509434,
        "final_val_acc": 0.839622641509434,
        "final_val_loss": 0.6618063233371051
      }
    },
    {
      "fold": 9,
      "val_acc": 0.7663551401869159,
      "test_acc": 0.6923076923076923,
      "test_loss": 0.5851333793411907,
      "best_override": {
        "set2set_steps": 3
      },
      "best_cfg": {
        "hidden_dim": 64,
        "num_conv_layers": 3,
        "dropout": 0.0,
        "lr": null,
        "pool_ratio": 0.5,
        "num_pools": 3,
        "sort_k": 30,
        "sort_conv1d_out": 32,
        "sort_conv1d_kernel": 5,
        "set2set_steps": 3,
        "set2set_layers": 1,
        "gmt_k": 30,
        "gmt_heads": 4,
        "gmt_encoder_blocks": 1,
        "gmt_dropout": 0.0,
        "gmt_layer_norm": false,
        "dense_pool_layers": 2,
        "diffpool_ratio_1": 0.25,
        "diffpool_ratio_2": 0.25,
        "mincut_ratio_1": 0.5,
        "mincut_ratio_2": 0.5,
        "diffpool_link_loss_weight": 1.0,
        "diffpool_entropy_loss_weight": 1.0,
        "mincut_loss_weight": 1.0,
        "mincut_ortho_loss_weight": 1.0,
        "dense_max_nodes": null,
        "dense_policy": "error",
        "degree_as_feature": true,
        "degree_onehot_cap": 100
      },
      "train_info": {
        "best_epoch": 10,
        "best_val_acc": 0.7663551401869159,
        "final_val_acc": 0.7663551401869159,
        "final_val_loss": 0.5827839296554851
      }
    },
    {
      "fold": 10,
      "val_acc": 0.7663551401869159,
      "test_acc": 0.7777777777777778,
      "test_loss": 0.5078586395989116,
      "best_override": {
        "set2set_steps": 6
      },
      "best_cfg": {
        "hidden_dim": 64,
        "num_conv_layers": 3,
        "dropout": 0.0,
        "lr": null,
        "pool_ratio": 0.5,
        "num_pools": 3,
        "sort_k": 30,
        "sort_conv1d_out": 32,
        "sort_conv1d_kernel": 5,
        "set2set_steps": 6,
        "set2set_layers": 1,
        "gmt_k": 30,
        "gmt_heads": 4,
        "gmt_encoder_blocks": 1,
        "gmt_dropout": 0.0,
        "gmt_layer_norm": false,
        "dense_pool_layers": 2,
        "diffpool_ratio_1": 0.25,
        "diffpool_ratio_2": 0.25,
        "mincut_ratio_1": 0.5,
        "mincut_ratio_2": 0.5,
        "diffpool_link_loss_weight": 1.0,
        "diffpool_entropy_loss_weight": 1.0,
        "mincut_loss_weight": 1.0,
        "mincut_ortho_loss_weight": 1.0,
        "dense_max_nodes": null,
        "dense_policy": "error",
        "degree_as_feature": true,
        "degree_onehot_cap": 100
      },
      "train_info": {
        "best_epoch": 40,
        "best_val_acc": 0.7663551401869159,
        "final_val_acc": 0.7663551401869159,
        "final_val_loss": 0.5628367099806527
      }
    }
  ],
  "train_cfg": {
    "seed": 45,
    "device": "cuda",
    "epochs": 300,
    "patience": 50,
    "batch_size": 64,
    "lr": 0.001,
    "weight_decay": 0.0,
    "val_ratio": 0.1,
    "num_workers": 0,
    "tune": true,
    "max_trials": 16,
    "log_every": 25,
    "save_dir": "./runs",
    "save_json": true
  },
  "base_model_cfg": {
    "hidden_dim": 64,
    "num_conv_layers": 3,
    "dropout": 0.0,
    "lr": null,
    "pool_ratio": 0.5,
    "num_pools": 3,
    "sort_k": 30,
    "sort_conv1d_out": 32,
    "sort_conv1d_kernel": 5,
    "set2set_steps": 3,
    "set2set_layers": 1,
    "gmt_k": 30,
    "gmt_heads": 4,
    "gmt_encoder_blocks": 1,
    "gmt_dropout": 0.0,
    "gmt_layer_norm": false,
    "dense_pool_layers": 2,
    "diffpool_ratio_1": 0.25,
    "diffpool_ratio_2": 0.25,
    "mincut_ratio_1": 0.5,
    "mincut_ratio_2": 0.5,
    "diffpool_link_loss_weight": 1.0,
    "diffpool_entropy_loss_weight": 1.0,
    "mincut_loss_weight": 1.0,
    "mincut_ortho_loss_weight": 1.0,
    "dense_max_nodes": null,
    "dense_policy": "error",
    "degree_as_feature": true,
    "degree_onehot_cap": 100
  }
}